urldecode_cli/__init__.py
urldecode_cli/__main__.py
urldecode_cli/cli.py
urldecode_cli-1.1.0.dist-info/METADATA
urldecode_cli-1.1.0.dist-info/WHEEL
urldecode_cli-1.1.0.dist-info/entry_points.txt
urldecode_cli-1.1.0.dist-info/RECORD
